opentelemetry/util/genai/evals/__init__.py
opentelemetry/util/genai/evals/admission_controller.py
opentelemetry/util/genai/evals/base.py
opentelemetry/util/genai/evals/bootstrap.py
opentelemetry/util/genai/evals/builtins.py
opentelemetry/util/genai/evals/defaults.py
opentelemetry/util/genai/evals/env.py
opentelemetry/util/genai/evals/errors.py
opentelemetry/util/genai/evals/manager.py
opentelemetry/util/genai/evals/normalize.py
opentelemetry/util/genai/evals/registry.py
opentelemetry/util/genai/evals/version.py
splunk_otel_util_genai_evals-0.1.7.dist-info/METADATA
splunk_otel_util_genai_evals-0.1.7.dist-info/WHEEL
splunk_otel_util_genai_evals-0.1.7.dist-info/entry_points.txt
splunk_otel_util_genai_evals-0.1.7.dist-info/licenses/LICENSE
splunk_otel_util_genai_evals-0.1.7.dist-info/RECORD
