Metadata-Version: 2.4
Name: splunk-otel-util-genai-evals
Version: 0.1.7
Summary: OpenTelemetry GenAI Evaluations
Project-URL: Homepage, https://github.com/open-telemetry/opentelemetry-python-contrib/tree/main/util/opentelemetry-util-genai
Project-URL: Repository, https://github.com/open-telemetry/opentelemetry-python-contrib
Author-email: OpenTelemetry Authors <cncf-opentelemetry-contributors@lists.cncf.io>
License-Expression: Apache-2.0
License-File: LICENSE
Classifier: Development Status :: 4 - Beta
Classifier: Intended Audience :: Developers
Classifier: License :: OSI Approved :: Apache Software License
Classifier: Programming Language :: Python
Classifier: Programming Language :: Python :: 3
Classifier: Programming Language :: Python :: 3.9
Classifier: Programming Language :: Python :: 3.10
Classifier: Programming Language :: Python :: 3.11
Classifier: Programming Language :: Python :: 3.12
Classifier: Programming Language :: Python :: 3.13
Requires-Python: >=3.9
Requires-Dist: splunk-otel-util-genai>=0.1.4
Provides-Extra: test
Requires-Dist: pytest>=7.0.0; extra == 'test'
